{
  "done": true,
  "migration": {
    "name": "mig_d10fd3qunsp1bris9rig",
    "operations": [
      {
        "add_column": {
          "up": "''",
          "table": "events",
          "column": {
            "name": "imageSrc",
            "type": "text",
            "comment": ""
          }
        }
      }
    ]
  },
  "migrationType": "pgroll",
  "name": "mig_d10fd3qunsp1bris9rig",
  "parent": "mig_d10fcmido80pli9qrc40",
  "schema": "public",
  "startedAt": "2025-06-05T01:44:48.460323Z"
}
